dropboxdrivefs/__init__.py
dropboxdrivefs/core.py
unstract_dropboxdrivefs-1.0.1.dist-info/LICENSE
unstract_dropboxdrivefs-1.0.1.dist-info/METADATA
unstract_dropboxdrivefs-1.0.1.dist-info/WHEEL
unstract_dropboxdrivefs-1.0.1.dist-info/top_level.txt
unstract_dropboxdrivefs-1.0.1.dist-info/RECORD
