Metadata-Version: 2.1
Name: unstract-dropboxdrivefs
Version: 1.0.1
Summary: Dropbox implementation by Unstract for fsspec module
Home-page: https://github.com/Zipstack/dropboxdrivefs/
Author: Zipstack Inc
Author-email: devsupport@zipstack.com
License: BSD
Platform: UNKNOWN
Classifier: Development Status :: 4 - Beta
Classifier: Intended Audience :: Developers
Classifier: License :: OSI Approved :: BSD License
Classifier: Operating System :: OS Independent
Classifier: Programming Language :: Python :: 3.5
Classifier: Programming Language :: Python :: 3.6
Classifier: Programming Language :: Python :: 3.7
Classifier: Programming Language :: Python :: 3.8
Classifier: Programming Language :: Python :: 3.9
Requires-Python: >=3.5
Requires-Dist: fsspec
Requires-Dist: requests
Requires-Dist: dropbox
